hla_compass/__init__.py
hla_compass/_version.py
hla_compass/auth.py
hla_compass/client.py
hla_compass/config.py
hla_compass/context.py
hla_compass/data.py
hla_compass/env.py
hla_compass/manifest.py
hla_compass/manifest_schema_v1.json
hla_compass/module.py
hla_compass/py.typed
hla_compass/signing.py
hla_compass/storage.py
hla_compass/types.py
hla_compass/utils.py
hla_compass/validation.py
hla_compass/cli/__init__.py
hla_compass/cli/__main__.py
hla_compass/cli/auth.py
hla_compass/cli/dev.py
hla_compass/cli/keys.py
hla_compass/cli/main.py
hla_compass/cli/module.py
hla_compass/cli/utils.py
hla_compass/data/openapi.mini.json
hla_compass/database/__init__.py
hla_compass/database/scientific_query.py
hla_compass/database/security.py
hla_compass/runtime/__init__.py
hla_compass/runtime/runner.py
hla_compass/templates/README.md
hla_compass/templates/STYLING_CHANGES.md
hla_compass/templates/no-ui-template/manifest.json
hla_compass/templates/no-ui-template/backend/main.py
hla_compass/templates/no-ui-template/backend/requirements.txt
hla_compass/templates/no-ui-template/examples/sample_input.json
hla_compass/templates/ui-template/manifest.json
hla_compass/templates/ui-template/backend/main.py
hla_compass/templates/ui-template/backend/requirements.txt
hla_compass/templates/ui-template/examples/sample_input.json
hla_compass/templates/ui-template/frontend/README.md
hla_compass/templates/ui-template/frontend/api.ts
hla_compass/templates/ui-template/frontend/index.tsx
hla_compass/templates/ui-template/frontend/package.json
hla_compass/templates/ui-template/frontend/standalone-entry.tsx
hla_compass/templates/ui-template/frontend/styles.css
hla_compass/templates/ui-template/frontend/theme.ts
hla_compass/templates/ui-template/frontend/tsconfig.json
hla_compass/templates/ui-template/frontend/variables.css
hla_compass/templates/ui-template/frontend/vite.config.ts
hla_compass/templates/ui-template/frontend/src/app/Providers.tsx
hla_compass-2.0.13.dist-info/METADATA
hla_compass-2.0.13.dist-info/WHEEL
hla_compass-2.0.13.dist-info/entry_points.txt
hla_compass-2.0.13.dist-info/top_level.txt
hla_compass-2.0.13.dist-info/RECORD
