Metadata-Version: 2.4
Name: hla-compass
Version: 2.0.13
Summary: Python SDK for HLA-Compass bioinformatics platform - Build powerful modules for immuno-peptidomics analysis
Author-email: Alithea Bio <armanas.povilionis@alithea.bio>
License: MIT
Project-URL: Bug Tracker, https://github.com/AlitheaBio/HLA-Compass-platform/issues
Project-URL: Documentation, https://docs.alithea.bio
Project-URL: Source Code, https://github.com/AlitheaBio/HLA-Compass-platform/tree/main/sdk/python
Classifier: Development Status :: 4 - Beta
Classifier: Intended Audience :: Developers
Classifier: Intended Audience :: Science/Research
Classifier: Topic :: Scientific/Engineering :: Bio-Informatics
Classifier: Topic :: Scientific/Engineering :: Medical Science Apps.
Classifier: License :: OSI Approved :: MIT License
Classifier: Programming Language :: Python :: 3
Classifier: Programming Language :: Python :: 3.8
Classifier: Programming Language :: Python :: 3.9
Classifier: Programming Language :: Python :: 3.10
Classifier: Programming Language :: Python :: 3.11
Classifier: Programming Language :: Python :: 3.12
Classifier: Programming Language :: Python :: 3.13
Classifier: Operating System :: OS Independent
Requires-Python: >=3.8
Requires-Dist: requests>=2.28.0
Requires-Dist: boto3>=1.26.0
Requires-Dist: click>=8.0.0
Requires-Dist: rich>=12.0.0
Requires-Dist: setuptools>=45.0.0
Requires-Dist: cryptography>=41.0.0
Requires-Dist: jsonschema>=4.17.0
Requires-Dist: pydantic>=2.0.0
Provides-Extra: dev
Requires-Dist: pip-tools>=7.0.0; extra == "dev"
Requires-Dist: pytest>=7.0.0; extra == "dev"
Requires-Dist: pytest-cov>=3.0.0; extra == "dev"
Requires-Dist: pytest-mock>=3.6.0; extra == "dev"
Requires-Dist: pytest-asyncio>=1.0.0; extra == "dev"
Requires-Dist: ruff>=0.1.0; extra == "dev"
Requires-Dist: mypy>=0.950; extra == "dev"
Requires-Dist: sphinx>=4.0.0; extra == "dev"
Requires-Dist: sphinx-rtd-theme>=1.0.0; extra == "dev"
Provides-Extra: data
Requires-Dist: pandas>=2.2.0; python_version >= "3.9" and extra == "data"
Requires-Dist: pandas<2.0,>=1.5; python_version < "3.9" and extra == "data"
Requires-Dist: xlsxwriter>=3.0.0; extra == "data"
Requires-Dist: polars>=0.20.0; python_version >= "3.9" and extra == "data"
Provides-Extra: ml
Requires-Dist: scikit-learn>=1.0.0; extra == "ml"
Requires-Dist: torch>=1.10.0; extra == "ml"
Requires-Dist: transformers>=4.20.0; extra == "ml"
